{
    "experiment_name": "stac_with_validation_4",
    "version_name": "stac_with_validation_4",

    "dataset": "voc2009",
    "data_path": ".",

    "model": "fasterrcnn",
    "experiment_description": "debugging",

    "momentum": 0.9,
    "seed": 47,
    "weight_decay": 0.0001,
    "batch_size": 8,
    "confidence_treshold": 0.9,
    "validation_part": 0,
    "num_workers": 1,

    "patience_epochs": 3,
    "min_epochs": 2,
    "max_epochs": 300,

    "learning_rate": 0.02,
    "gradient_clip_threshold": 0,
    "min_lr_ratio": 0.004,

    "num_warmup_steps": 250,
    "initial_total_steps": 1000,

    "total_steps": 1000,

    "num_labelled_samples": 220,
    "consistency_lambda": 2,
    "max_lam": 1,
    "consistency_criterion": "KL",
    "classifier_type": "added",

    "with_TSA": "True",
    "TSA_proba_min": 0.1,
    "TSA_proba_max": 1.0,

    "no_UDA": "False",
    "with_SWA": "False"
}
